odoo10_addon_shopinvader_payment_adyen-10.0.1.0.0.99.dev12-nspkg.pth
odoo/addons/shopinvader_payment_adyen/README.rst
odoo/addons/shopinvader_payment_adyen/__init__.py
odoo/addons/shopinvader_payment_adyen/__manifest__.py
odoo/addons/shopinvader_payment_adyen/demo/shopinvader_payment_demo.xml
odoo/addons/shopinvader_payment_adyen/readme/CONTRIBUTORS.rst
odoo/addons/shopinvader_payment_adyen/readme/DESCRIPTION.rst
odoo/addons/shopinvader_payment_adyen/services/__init__.py
odoo/addons/shopinvader_payment_adyen/services/cart.py
odoo/addons/shopinvader_payment_adyen/services/payment_service.py
odoo/addons/shopinvader_payment_adyen/static/description/index.html
odoo/addons/shopinvader_payment_adyen/tests/__init__.py
odoo/addons/shopinvader_payment_adyen/tests/test_payment.py
odoo/addons/shopinvader_payment_adyen/tests/fixtures/cassettes/test_create_transaction_3d_required_failed.yaml
odoo/addons/shopinvader_payment_adyen/tests/fixtures/cassettes/test_create_transaction_3d_required_success.yaml
odoo/addons/shopinvader_payment_adyen/tests/fixtures/cassettes/test_create_transaction_france.yaml
odoo/addons/shopinvader_payment_adyen/tests/fixtures/cassettes/test_create_transaction_mastecard.yaml
odoo/addons/shopinvader_payment_adyen/tests/fixtures/cassettes/test_create_transaction_us.yaml
odoo/addons/shopinvader_payment_adyen/tests/fixtures/cassettes/test_create_transaction_wrong_cvc.yaml
odoo/addons/shopinvader_payment_adyen/tests/fixtures/cassettes/test_create_transaction_wrong_expiry.yaml
odoo/addons/shopinvader_payment_adyen/tests/fixtures/cassettes/test_create_transaction_wrong_number.yaml
odoo/addons/shopinvader_payment_adyen/tests/fixtures/cassettes/test_wrong_api_key.yaml
odoo10_addon_shopinvader_payment_adyen-10.0.1.0.0.99.dev12.dist-info/METADATA
odoo10_addon_shopinvader_payment_adyen-10.0.1.0.0.99.dev12.dist-info/WHEEL
odoo10_addon_shopinvader_payment_adyen-10.0.1.0.0.99.dev12.dist-info/namespace_packages.txt
odoo10_addon_shopinvader_payment_adyen-10.0.1.0.0.99.dev12.dist-info/top_level.txt
odoo10_addon_shopinvader_payment_adyen-10.0.1.0.0.99.dev12.dist-info/RECORD
